langgraph_openai_serve/__init__.py
langgraph_openai_serve/openai_server.py
langgraph_openai_serve/api/__init__.py
langgraph_openai_serve/api/chat/__init__.py
langgraph_openai_serve/api/chat/service.py
langgraph_openai_serve/api/chat/views.py
langgraph_openai_serve/api/health/__init__.py
langgraph_openai_serve/api/health/views.py
langgraph_openai_serve/api/models/__init__.py
langgraph_openai_serve/api/models/service.py
langgraph_openai_serve/api/models/views.py
langgraph_openai_serve/graph/__init__.py
langgraph_openai_serve/graph/runner.py
langgraph_openai_serve/graph/simple_graph.py
langgraph_openai_serve/schemas/__init__.py
langgraph_openai_serve/schemas/openai_schema.py
langgraph_openai_serve/utils/__init__.py
langgraph_openai_serve/utils/message.py
langgraph_openai_serve-0.0.1.dist-info/METADATA
langgraph_openai_serve-0.0.1.dist-info/WHEEL
langgraph_openai_serve-0.0.1.dist-info/licenses/LICENSE
langgraph_openai_serve-0.0.1.dist-info/RECORD
