Metadata-Version: 2.4
Name: langgraph_openai_serve
Version: 0.0.1
Summary: Openai Compatible Langgraph Server
Author-email: İlker SIĞIRCI <sigirci.ilker@gmail.com>
Maintainer-email: İlker SIĞIRCI <sigirci.ilker@gmail.com>
License-File: LICENSE
Keywords: langgraph_openai_serve
Classifier: Intended Audience :: Developers
Classifier: Intended Audience :: Science/Research
Classifier: License :: OSI Approved :: BSD License
Classifier: Operating System :: MacOS
Classifier: Operating System :: Microsoft :: Windows
Classifier: Operating System :: POSIX
Classifier: Operating System :: Unix
Classifier: Programming Language :: Python
Classifier: Programming Language :: Python :: 3.11
Classifier: Programming Language :: Python :: 3.12
Classifier: Topic :: Scientific/Engineering
Classifier: Topic :: Software Development
Requires-Python: <3.13,>=3.11
Requires-Dist: fastapi[standard]>=0.115.12
Requires-Dist: langchain-openai>=0.3.13
Requires-Dist: langgraph>=0.3.30
